setup.py
ppp_spell_checker/__init__.py
ppp_spell_checker/requesthandler.py
ppp_spell_checker.egg-info/PKG-INFO
ppp_spell_checker.egg-info/SOURCES.txt
ppp_spell_checker.egg-info/dependency_links.txt
ppp_spell_checker.egg-info/requires.txt
ppp_spell_checker.egg-info/top_level.txt